[
  {
    "character": "二乃",
    "japanese": "さあ！\n今日と明日は思いっきり夏を楽しむわよ！",
    "translation": "Alright! Let's make the most out of our summer, \ntoday and tomorrow!"
  },
  {
    "character": "五月",
    "japanese": "楽しむことはもちろんですが、\n節度ある行動を心がけましょう。",
    "translation": "Of course, we should have fun,\nbut let's also make sure to act with moderation."
  },
  {
    "character": "二乃",
    "japanese": "……あんた頭が固すぎ。\nいきなり空気読まない発言は止めなさいよね。",
    "translation": "...You're too stubborn.\nStop making sudden statements without considering\nthe atmosphere."
  },
  {
    "character": "一花",
    "japanese": "まあまあ、そう言わない。\n羽目を外しすぎて怪我なんかしたら、\nせっかくのバカンスが台無しになっちゃうし。",
    "translation": "Now, now, don't say that.\nIf we cut loose too much and get hurt,\nour precious vacation will be ruined."
  },
  {
    "character": "五月",
    "japanese": "そうです、みんなが無事に島を出ることで\n楽しい想い出となるのですから。\n上杉君もわかっていますよね？",
    "translation": "That's right, it will become a fun memory for everyone\nif we all leave the island safely.\nUesugi-kun, you understand that too, right?"
  },
  {
    "character": "風太郎",
    "japanese": "（なぜ俺だけ念を押されるんだ……）",
    "translation": "(Why am I the only one being reminded...)"
  },
  {
    "character": "三玖",
    "japanese": "それじゃ、今日はなにする？",
    "translation": "Alright, so what are we going to do today?"
  },
  {
    "character": "四葉",
    "japanese": "はいはーい！\n今日は探検をしようよ！",
    "translation": "Hey, heeey!\nLet's explore today!"
  },
  {
    "character": "らいは",
    "japanese": "あっ！　私も！\n探検してみたい！",
    "translation": "Ah! Me too!\nI want to try exploring too!"
  },
  {
    "character": "二乃",
    "japanese": "探検？\nこの暑いのに山にでも行くわけ？",
    "translation": "Exploring?\nAre we going to climb the mountain in this heat?"
  },
  {
    "character": "四葉",
    "japanese": "山じゃなくて、この島に住んでいた人たちの足跡を\nたどってみたりできないかなって。",
    "translation": "Not the mountain,\nbut maybe we could follow the footsteps of the people\nwho used to live on this island."
  },
  {
    "character": "らいは",
    "japanese": "うん、ちょっと面白そうだよね。",
    "translation": "Yeah, that sounds interesting."
  },
  {
    "character": "風太郎",
    "japanese": "（……さては昨日見つけた本に影響されたな？）",
    "translation": "(...Did they perhaps get influenced\n by the book they found yesterday?)"
  },
  {
    "character": "五月",
    "japanese": "確か、少し離れたところに集落の跡は\nありましたが……あそこですか？",
    "translation": "I remember there were remains of a village\na little further away... \nDo you mean you want to go there?"
  },
  {
    "character": "五月",
    "japanese": "腐食の進んでいる建物もあるようでしたし\n危険なのでは……。",
    "translation": "There seemed to be some buildings that were corroding,\nso it might be dangerous..."
  },
  {
    "character": "四葉",
    "japanese": "大丈夫！\n家の中に入るとか、危ないことはしないよ。\nちょっと外から見てみるだけだから。",
    "translation": "It's alright!\nWe won't go inside any houses or do anything dangerous.\nWe'll just take a look from the outside."
  },
  {
    "character": "二乃",
    "japanese": "ねえ、それより海で泳ぐほうがよくない？\nせっかく水着を持ってきたのに、\n着る機会が少なすぎよ。",
    "translation": "Hey, wouldn't it be better to swim in the sea?\nWe brought our swimsuits,\nbut haven't had enough chances to wear them."
  },
  {
    "character": "五月",
    "japanese": "私は探検に賛成です！\n探検となれば、健全で楽しそうですから！",
    "translation": "I'm in favor of exploring!\nIt seems healthy and fun!"
  },
  {
    "character": "二乃",
    "japanese": "急に意見変えたわね……。",
    "translation": "You suddenly changed your mind..."
  },
  {
    "character": "五月",
    "japanese": "そ、そんなことはありませんよぉ～？",
    "translation": "Th-that's not true, you know?"
  },
  {
    "character": "一花",
    "japanese": "私はどっちでもいいかなー。\nフータロー君は？",
    "translation": "I'm fine with either.\nHow about you, Futaro-kun?"
  },
  {
    "character": "風太郎",
    "japanese": "探検でいいんじゃないか？\nらいはが行きたいって言ってるしな。",
    "translation": "Going exploring sounds fun, huh?\nRaiha says she'd like to go, too."
  },
  {
    "character": "二乃",
    "japanese": "言うと思ったわ。",
    "translation": "I thought you'd say that."
  },
  {
    "character": "一花",
    "japanese": "明日もあるんだし\n今日は探検ってことでいいんじゃない？",
    "translation": "Since we have tomorrow as well,\nwhy don't we go on an adventure today?"
  },
  {
    "character": "三玖",
    "japanese": "ならお弁当は任せて。\n美味しいの作るから。",
    "translation": "Then leave the lunch to me.\nI'll make something delicious for everyone."
  },
  {
    "character": "二乃",
    "japanese": "まさか、三玖１人で全員分を作るつもり？",
    "translation": "Are you really planning to make lunch for everyone\nby yourself?"
  },
  {
    "character": "三玖",
    "japanese": "大丈夫。\nこの島に来てから、たくさん修行したし。",
    "translation": "I'll be okay.\nI've trained a lot since coming to this island."
  },
  {
    "character": "二乃",
    "japanese": "あんた１人じゃまだまだ不安なの。\n手伝ってあげるから、ちゃんと覚えるのよ？",
    "translation": "I'm still worried if it's just you.\nI'll help you so that you can learn more, okay?"
  },
  {
    "character": "三玖",
    "japanese": "二乃がそこまで言うなら……助手で。",
    "translation": "If you say so, Nino... You can be my assistant."
  },
  {
    "character": "二乃",
    "japanese": "はいはい、それでいいから。\n早く作りましょ。",
    "translation": "Okay, that's fine, then.\nLet's hurry up and start cookin'."
  },
  {
    "character": "らいは",
    "japanese": "私もお手伝いするー！",
    "translation": "I'll help too!"
  },
  {
    "character": "四葉",
    "japanese": "私はその間に探検の準備をしておくね！",
    "translation": "I'll get prepared for our exploration in the meantime!"
  },
  {
    "character": "五月",
    "japanese": "手伝いますよ、四葉。",
    "translation": "I'll help you, Yotsuba."
  },
  {
    "character": "一花",
    "japanese": "じゃあ、お弁当係と準備係に分かれよっか。",
    "translation": "Alright, let's split into the lunch team\nand preparation team."
  },
  {
    "character": "風太郎",
    "japanese": "そうだな。\nよし、とっととやるか。",
    "translation": "Right.\nWell, let's get to it."
  }
]