[
  {
    "character": "風太郎",
    "japanese": "今日の昼は唐揚げか。",
    "translation": "Fried chicken today, huh."
  },
  {
    "character": "五月",
    "japanese": "んんん……。\nなんだか……ゴムを食べているみたいです。",
    "translation": "Hmmm...\nIt kind of feels like...I'm eating rubber."
  },
  {
    "character": "二乃",
    "japanese": "あーあ、これ揚げすぎよ。\n肉が固くなっちゃってるもの。",
    "translation": "Aaaah, this is way too overcooked.\nThe meat is way too hard."
  },
  {
    "character": "らいは",
    "japanese": "ということは……これ全部失敗なのかなぁ。",
    "translation": "That means...this was all a failure."
  },
  {
    "character": "風太郎",
    "japanese": "固いが食えないことはないさ。\nよし、頑張って消費するぞ！",
    "translation": "Just because it's hard doesn't mean we can't eat it.\nAlright, let's do our best to consume it!"
  }
]