[
  {
    "character": "風太郎",
    "japanese": "すう……すう……。",
    "translation": "*snore*"
  },
  {
    "character": "風太郎",
    "japanese": "むにゃ……。",
    "translation": "Mmmhh..."
  },
  {
    "character": "三玖",
    "japanese": "…………。",
    "translation": "......"
  },
  {
    "character": "風太郎",
    "japanese": "……！",
    "translation": "...!"
  },
  {
    "character": "風太郎",
    "japanese": "（なんだ？\n　今、音がしたような……）",
    "translation": "(Hm?\n Did I, just hear something...?)"
  },
  {
    "character": "三玖",
    "japanese": "…………。",
    "translation": "......"
  },
  {
    "character": "風太郎",
    "japanese": "（人の気配が……　誰か部屋にいる？\n　そうか、今のはドアを閉めた音か）",
    "translation": "(I can feel someone's presence... Is someone in the room?\n Ah, that noise was the door shutting.)"
  },
  {
    "character": "三玖",
    "japanese": "…………。",
    "translation": "......"
  },
  {
    "character": "風太郎",
    "japanese": "（こっちに近づいて来た？\n　しかし起こしに来てくれたにしては妙だな。\n　どうして息を潜めてるんだ？）",
    "translation": "(I can sense them getting closer?\n Why are they holding their breath\n if they are just trying to wake me up?)"
  },
  {
    "character": "風太郎",
    "japanese": "（！！　さては二乃か一花あたりが\n　なんか仕掛けるつもりだな？）",
    "translation": "(It's probably Nino or Ichika trying to pull a prank on me.)"
  },
  {
    "character": "風太郎",
    "japanese": "（ふん、お見通しなんだよ。\n　そっちがそういうつもりなら……\n　返り討ちにしてくれる！）",
    "translation": "(Hmph, I see through their tricks.\n If that's the case...\n Why don't I turn the tables?!)"
  },
  {
    "character": "風太郎",
    "japanese": "…………。",
    "translation": "......"
  },
  {
    "character": "三玖",
    "japanese": "…………。",
    "translation": "......"
  },
  {
    "character": "風太郎",
    "japanese": "…………。",
    "translation": "......"
  },
  {
    "character": "三玖",
    "japanese": "…………。",
    "translation": "......"
  },
  {
    "character": "風太郎",
    "japanese": "（あれ？　仕掛けてこない？）",
    "translation": "(Hm? Why aren't they making a move?)"
  },
  {
    "character": "三玖",
    "japanese": "……フータロー。",
    "translation": "...Futaro."
  },
  {
    "character": "風太郎",
    "japanese": "（あれ、今の声は……）",
    "translation": "(Ah, I recognize that voice...)"
  },
  {
    "character": "風太郎",
    "japanese": "三玖か？",
    "translation": "Is it Miku?"
  },
  {
    "character": "三玖",
    "japanese": "……あ。\nえ、え、え、なんで起きて！？",
    "translation": "...Ah.\nWh-wh-wh-why are you awake?!"
  },
  {
    "character": "風太郎",
    "japanese": "うわっ！？\nお前、近すぎ――",
    "translation": "UWAA?!\nYou're too close%p-2;――"
  },
  {
    "character": "三玖",
    "japanese": "いたっ！？",
    "translation": "OUCH!"
  },
  {
    "character": "風太郎",
    "japanese": "ってえ……！",
    "translation": "OWW...!"
  },
  {
    "character": "三玖",
    "japanese": "うううう……おでこ痛い……。",
    "translation": "Oooohhh... My forehead..."
  },
  {
    "character": "風太郎",
    "japanese": "す、すまん三玖、大丈夫か？",
    "translation": "S-sorry Miku, are you okay?"
  },
  {
    "character": "三玖",
    "japanese": "大丈夫。\nフータローこそ平気？",
    "translation": "I'm okay.\nAre you okay, Futaro?"
  },
  {
    "character": "風太郎",
    "japanese": "ああ、むしろいい目覚ましになったよ。",
    "translation": "Yeah, now I'm wide awake, thanks for that."
  },
  {
    "character": "三玖",
    "japanese": "フータロー、なんで急に起きるの。",
    "translation": "Futaro, why did you spring out of your bed so quickly?"
  },
  {
    "character": "風太郎",
    "japanese": "なんでってビックリしてとっさにだな。\nお前こそなにしてたんだよ、あんなに近くで。",
    "translation": "What do you mean why? It's because you surprised me.\nWhat were you doing, so close to me?"
  },
  {
    "character": "三玖",
    "japanese": "えっ！？\nそれは、その、起こそうと思って。",
    "translation": "WHA?!\nWell, I, just thought, I'd wake you up."
  },
  {
    "character": "風太郎",
    "japanese": "だったら普通に声をかけてくれよ。",
    "translation": "In that case, you could have wake me up normally."
  },
  {
    "character": "風太郎",
    "japanese": "ていうか顔が真っ赤だぞ？\n変なところを打ったんじゃないか？",
    "translation": "But anyway, your face is bright red.\nDid you hit your head or something?"
  },
  {
    "character": "三玖",
    "japanese": "ううん、平気。\nおでこをぶつけただけだから。",
    "translation": "No, I'm okay.\nI just hit my forehead that's all."
  },
  {
    "character": "三玖",
    "japanese": "……もうちょっとで\n唇がぶつかっちゃうかと思ったけど。",
    "translation": "...I thought our lips were going to collide."
  },
  {
    "character": "風太郎",
    "japanese": "は？\nいや、それは……まあ、あり得たかもしれんが。",
    "translation": "Huh?\nUm, that's... Well, that was a possibility."
  },
  {
    "character": "三玖",
    "japanese": "もしそうなってたらフータローはどうする？\n責任取ってくれる？",
    "translation": "What would you have done if that had happened, Futaro?\nWould you have taken responsibility?"
  },
  {
    "character": "風太郎",
    "japanese": "あ、朝から変なことを言い出すんじゃない。\nほら、俺は着替えるから出て行ってくれ。",
    "translation": "Oh, can you not make it so awkward early in the morning.\nLook, I'm going to get dressed, so get out."
  },
  {
    "character": "三玖",
    "japanese": "うん、わかった。",
    "translation": "Okay, got it."
  }
]