[
  {
    "character": "風太郎",
    "japanese": "（今日も１日よく動いたな。\n　さすがに、この時間になると眠くなる）",
    "translation": "(Today was another busy one.\n Figures I'd be sleepy by this time.)"
  },
  {
    "character": "風太郎",
    "japanese": "（……ん？　誰かリビングにいるな）",
    "translation": "(...Hm? Someone's in the living room.)"
  },
  {
    "character": "五月",
    "japanese": "…………。",
    "translation": "......"
  },
  {
    "character": "風太郎",
    "japanese": "（五月か。\n　熱中して何を……ああ、また勉強してるのか）",
    "translation": "(Itsuki, huh.\n What's she so enthusiastic about... \n Ah, she's studying again.)"
  },
  {
    "character": "五月",
    "japanese": "…………。",
    "translation": "......"
  },
  {
    "character": "風太郎",
    "japanese": "よお、またこんな時間まで勉強か。",
    "translation": "Yo, you're studying at this time again?"
  },
  {
    "character": "五月",
    "japanese": "受験生ですから当たり前です。\nそれに、一学期に受けた模試が……。",
    "translation": "Obviously. We are entrance exam students.\nAlso, the mock exam we had in the first semester..."
  },
  {
    "character": "風太郎",
    "japanese": "模試がどうした？\nあれの結果が返ってくるのは二学期だろう？",
    "translation": "What about the mock exam?\nThe results will come in the second semester,\nright?"
  },
  {
    "character": "五月",
    "japanese": "結果はまだですが、\n正直あまり手応えを感じられなかったので。",
    "translation": "We don't have the results yet,\nbut to be honest, I didn't feel very satisfied."
  },
  {
    "character": "風太郎",
    "japanese": "なるほどな。\n慢心しないのはいいことだ。",
    "translation": "I see.\nIt's good you're not too confident."
  },
  {
    "character": "五月",
    "japanese": "え？",
    "translation": "Huh?"
  },
  {
    "character": "風太郎",
    "japanese": "不安を感じるのは、自分自身に足りないものがあると\n自覚しているからこそだ。",
    "translation": "The reason you feel uneasy is because you've realized\nyou're lacking something within."
  },
  {
    "character": "風太郎",
    "japanese": "中には、模試で手応えがあったからと油断し\n夏休みを無駄にするようなやつもいる。\nお前は、その心配はないようだな。",
    "translation": "Some get caught off guard and waste their summer\nvacation just because they did well in the mock exam.\nYou don't seem to have to worry about that."
  },
  {
    "character": "五月",
    "japanese": "……ええ。\nこの夏が正念場だということはわかっています。",
    "translation": "...Yes.\nAnd I know this summer is a critical moment."
  },
  {
    "character": "風太郎",
    "japanese": "自己採点は当然したよな？\n間違えたところを見直して、\nまた出たら答えられるようにしておけ。",
    "translation": "You self-graded, didn't you?\nReview your mistakes\nand be ready to answer when they come up again."
  },
  {
    "character": "五月",
    "japanese": "それもわかっています！",
    "translation": "I understand that, too!"
  },
  {
    "character": "五月",
    "japanese": "あ、すみません。\nこんな、あなたに当たるようなことを……。",
    "translation": "Ah, excuse me.\nI didn't really mean to lash out like that..."
  },
  {
    "character": "風太郎",
    "japanese": "気にするな。\n生徒の不安を受け止めるのも家庭教師の仕事だ。",
    "translation": "Don't fret.\nIt's the job of a tutor\nto accept the anxiety of their students."
  },
  {
    "character": "五月",
    "japanese": "……すみません。",
    "translation": "...I'm sorry."
  },
  {
    "character": "風太郎",
    "japanese": "だから、なんで謝るんだよ。\nお前が妙にしおらしいとこっちも調子が悪くなるだろ。",
    "translation": "Why are you apologizing?\nIf you're acting strange,\nit'll make me feel weird."
  },
  {
    "character": "五月",
    "japanese": "なっ……！\nもう、あなたは本当に……。",
    "translation": "WHA...!\nYou are truly, such a..."
  },
  {
    "character": "風太郎",
    "japanese": "どうする？　勉強見てやろうか？",
    "translation": "What do you wanna do?\nShould I take a look at your studies?"
  },
  {
    "character": "五月",
    "japanese": "いえ、あなたもお疲れでしょう？\n私もそろそろ寝ようと思っていましたので。",
    "translation": "No, you're tired too, aren't you?\nI thought I should head to bed soon, as well."
  },
  {
    "character": "風太郎",
    "japanese": "そうか、じゃあまた明日な。",
    "translation": "Alright, then I'll see you tomorrow."
  },
  {
    "character": "五月",
    "japanese": "おやすみなさい、上杉君。\n……その、ありがとうございました。",
    "translation": "Good night, Uesugi-kun.\n...And, thanks a lot."
  }
]