[
  {
    "character": "一花",
    "japanese": "はーい。",
    "translation": "Alrighty."
  },
  {
    "character": "五月",
    "japanese": "お邪魔します。\nらいはちゃんを連れてきましたよ。",
    "translation": "Good evening.\nI brought Raiha-chan with me."
  },
  {
    "character": "らいは",
    "japanese": "こんばんはー。",
    "translation": "Good evening."
  },
  {
    "character": "一花",
    "japanese": "いらっしゃーい。",
    "translation": "Welcome."
  },
  {
    "character": "二乃",
    "japanese": "これで全員揃ったわね。",
    "translation": "Now we're all here."
  },
  {
    "character": "らいは",
    "japanese": "ねえ、こうして集まったのって、\nもしかしてお兄ちゃんと四葉さんのこと？",
    "translation": "Hey, did we all gather like this\nbecause of big bro and Yotsuba-san?"
  },
  {
    "character": "二乃",
    "japanese": "ええ、そういうこと。\nわかってるわねー、らいはちゃん。\nこれは心強いわ。",
    "translation": "Yes, that's right.\nYou're sharp, Raiha-chan.\nThat's reassuring."
  },
  {
    "character": "五月",
    "japanese": "２人はどこに？",
    "translation": "Where are those two?"
  },
  {
    "character": "二乃",
    "japanese": "ラウンジで夜景を見てるはずよ。\nそう仕向けたから。",
    "translation": "They should be in the lounge\nlooking at the night view."
  },
  {
    "character": "五月",
    "japanese": "えっ？　仕向けた？",
    "translation": "Eh? You set it up?"
  },
  {
    "character": "三玖",
    "japanese": "五月……。",
    "translation": "Itsuki..."
  },
  {
    "character": "五月",
    "japanese": "な、なぜがっかりしてるんですか！？",
    "translation": "Wh-why are you disappointed?!"
  },
  {
    "character": "二乃",
    "japanese": "夜景を見ながら語り合うなんてデートの定番じゃない。\n今頃、キスくらいしてるかもね。",
    "translation": "Watching the night view while talking together\nis a classic date.\nThey might even be kissing by now."
  },
  {
    "character": "五月",
    "japanese": "はいっ！？",
    "translation": "WHA?!"
  },
  {
    "character": "らいは",
    "japanese": "おおおお～！\nお兄ちゃんが大人の階段を！",
    "translation": "Oooohh!\nBig bro's first steps to becoming a man!"
  },
  {
    "character": "一花",
    "japanese": "いやー、フータロー君に\nそこまでの度胸あるかなぁ？",
    "translation": "Well, I wonder if Futaro-kun\nhas the courage to go that far?"
  },
  {
    "character": "三玖",
    "japanese": "ない。",
    "translation": "Nope."
  },
  {
    "character": "一花",
    "japanese": "わお、断言されたよ。",
    "translation": "Wow, a declaration."
  },
  {
    "character": "五月",
    "japanese": "今日の三玖は容赦がありませんね。",
    "translation": "You're ruthless today, Miku."
  },
  {
    "character": "三玖",
    "japanese": "私は思ったことを言っただけ。\nあの２人、未だに付き合ってるように見えないし。",
    "translation": "I just said what was on my mind.\nThose two don't look like they're dating yet."
  },
  {
    "character": "二乃",
    "japanese": "そうよね。\n普通、もっと２人っきりになりたいと思ったり\nペアを組めたら喜ぶものじゃないの？",
    "translation": "That's true.\nNormally, they would be happy to be alone together\nor team up as a pair, wouldn't they?"
  },
  {
    "character": "一花",
    "japanese": "昼間、それとなく誘導はしてみたんだけどね。\nまったくと言っていいほど\n気がついてもらえなかったよ。",
    "translation": "I tried to lead them in that direction during the day,\nbut like, they didn't seem to notice at ALL."
  },
  {
    "character": "五月",
    "japanese": "私も一応、事と次第によっては\n気を遣う準備をしていましたが、\nそんな雰囲気はまったくなくて……。",
    "translation": "I also prepared myself to be considerate\ndepending on how their situation was,\nbut there was no such kind of atmosphere..."
  },
  {
    "character": "二乃",
    "japanese": "あれじゃ、いままでとなにも変わらないじゃない。\nフー君が四葉に告白してからもう半年なのよ？",
    "translation": "Well now, nothing has changed since then.\nIt's been half a year since Fu-kun\nconfessed to Yotsuba."
  },
  {
    "character": "三玖",
    "japanese": "いままで大学受験で忙しかったから、\n仕方ないところはあると思う。",
    "translation": "He was busy with college exams until now, so\nI think there's no choice but to accept that."
  },
  {
    "character": "三玖",
    "japanese": "でも、その受験からもようやく開放されたんだし、\n少しくらいなら許せるのに。",
    "translation": "But now that Futaro's finally released\nfrom those exams,\nI think he can let loose a little bit."
  },
  {
    "character": "一花",
    "japanese": "本当に許せる？",
    "translation": "Do you think he can really do that?"
  },
  {
    "character": "三玖",
    "japanese": "目の前でイチャイチャされたら、\nそれはそれで問題ありだけど……。",
    "translation": "If they start getting lovey-dovey in front of us,\nthat would be a problem too..."
  },
  {
    "character": "二乃",
    "japanese": "ま、本人たちにその気がなかったとしても\n当てつけられてるようでつらいかもね。",
    "translation": "W-well, even if they didn't have those feelings,\nit might be tough if they felt\nlike they were being pressured."
  },
  {
    "character": "二乃",
    "japanese": "でも、恋人らしいことをしてくれないのも、\n気を遣われてるみたいで癪なのよ。",
    "translation": "But not doing things that a couple should do\nmakes me feel uneasy,\nlike they're trying to be considerate."
  },
  {
    "character": "五月",
    "japanese": "ですが、あまり干渉しすぎるのはどうなんでしょう。\n２人の問題なのですから。",
    "translation": "But, shouldn't we be careful not to interfere too much?\nIt's their problem after all."
  },
  {
    "character": "二乃",
    "japanese": "２人の問題は私たち姉妹の問題よ。\nあと、らいはちゃんの問題でもあるんじゃない？",
    "translation": "As her sisters, their problem is our problem.\nAlso, it's Raiha-chan's problem, isn't it?"
  },
  {
    "character": "三玖",
    "japanese": "それにフータローはもうすぐ上京する。",
    "translation": "Besides, Futaro is going to Tokyo soon."
  },
  {
    "character": "二乃",
    "japanese": "そう！　そこよ！",
    "translation": "Right! That's it!"
  },
  {
    "character": "二乃",
    "japanese": "新しい場所で慣れない一人暮らし。\n普段らいはちゃんに頼りきりだったフー君には\n大した生活力もない。",
    "translation": "Living alone in an unfamiliar place.\nFu-kun has been completely dependent on Raiha-chan\nup until now. He doesn't have many life skills."
  },
  {
    "character": "らいは",
    "japanese": "うーん、確かに。\n朝１人で起きられるかも心配だもん。",
    "translation": "Hmm, that's true.\nI'm worried if he'll be able to\nwake up alone in the morning."
  },
  {
    "character": "二乃",
    "japanese": "そんな心細い大学生活を送るフー君の前に\nもし、新たな恋のライバルが現れたら――",
    "translation": "If a new woman appears in front of Fu-kun,\nwho's really the one who is\ngoing to have a lonely college life%p-2;――"
  },
  {
    "character": "二乃",
    "japanese": "いまの四葉じゃ勝ち目がないかもしれないわ！",
    "translation": "Yotsuba as she is now might have\nno chance against them!"
  },
  {
    "character": "三玖",
    "japanese": "それに、四葉には遠距離恋愛ってハンデもある。",
    "translation": "Besides, long-distance relationships\nwould also be a handicap for Yotsuba."
  },
  {
    "character": "一花",
    "japanese": "２人の気持ちを疑う気はないけど、\nやっぱり遠距離ってのはつらいよね。",
    "translation": "I don't doubt their feelings,\nbut long-distance is tough, isn't it?"
  },
  {
    "character": "二乃",
    "japanese": "なんであろうと、ここで四葉が\n赤の他人に負けるなんて許されないわ！",
    "translation": "However, no matter what, it's unacceptable for Yotsuba\nto lose to a stranger here!"
  },
  {
    "character": "三玖",
    "japanese": "私も絶対に受け入れられない。",
    "translation": "I wouldn't accept it either."
  },
  {
    "character": "五月",
    "japanese": "あのぅ、話が飛躍しすぎでは？\nそもそも、上杉君はお世辞にも\n女性に好かれる性格ではありませんよ？",
    "translation": "Umm, isn't the conversation jumping around too much?\nBesides, Uesugi-kun is not the kind of person\nwho is very popular with women, to put it politely."
  },
  {
    "character": "一花",
    "japanese": "なにげにひどいね五月ちゃん。",
    "translation": "That's kind of harsh, Itsuki-chan."
  },
  {
    "character": "一花",
    "japanese": "けどフータロー君って、\nああ見えて天然たらしだからねー。",
    "translation": "But Futaro-kun is naturally clumsy, you know?"
  },
  {
    "character": "五月",
    "japanese": "え？",
    "translation": "Huh?"
  },
  {
    "character": "三玖",
    "japanese": "だから困る。",
    "translation": "That's why I'm worried."
  },
  {
    "character": "二乃",
    "japanese": "五月だってフー君のこと好きでしょ？",
    "translation": "Itsuki, you also like Fu-kun, right?"
  },
  {
    "character": "五月",
    "japanese": "す、好きだなんてそんなことはっ！？",
    "translation": "W-what do you mean, I LIKE him?!"
  },
  {
    "character": "二乃",
    "japanese": "友人としてよ。",
    "translation": "As a friend."
  },
  {
    "character": "五月",
    "japanese": "そ、それは、もちろん。\n友人としては尊敬もしています。",
    "translation": "Well, of course. I respect him as a friend."
  },
  {
    "character": "二乃",
    "japanese": "だったらわかるでしょ？\nフー君がどれだけ素敵な人なのか。",
    "translation": "Then you understand, don't you?\nHow wonderful Fu-kun is."
  },
  {
    "character": "五月",
    "japanese": "ええ、まあ。",
    "translation": "Well, I suppose."
  },
  {
    "character": "らいは",
    "japanese": "お兄ちゃんがこんなに高評価なんて……！",
    "translation": "I'm so happy to hear my brother praised so highly!"
  },
  {
    "character": "五月",
    "japanese": "らいはちゃんが言ったとおりだったからですよ。\n確かに、彼には良いところがたくさんありました。",
    "translation": "I totally agree Raiha-chan.\nCertainly, he has many good points."
  },
  {
    "character": "らいは",
    "japanese": "うん、すごく嬉しい……。",
    "translation": "Yeah, I'm REALLY happy..."
  },
  {
    "character": "二乃",
    "japanese": "話を戻すけれど、フー君と四葉のこれからのためにも\nここで荒療治が必要だと思うのよ。",
    "translation": "Anyway, getting back onto the subject.\nI think we need to take drastic action\nfor Fu-kun and Yotsuba's future."
  },
  {
    "character": "五月",
    "japanese": "えっ！？\nなにをするつもりなのですか？\n手荒なことはダメですよ？",
    "translation": "WHA?! What are you planning to do?\nWe have to treat this matter delicately, you know?"
  },
  {
    "character": "二乃",
    "japanese": "しないわよ、手荒なことなんて。",
    "translation": "I wouldn't dare to treat anything so gracelessly."
  },
  {
    "character": "三玖",
    "japanese": "二乃が言っても説得力ない。",
    "translation": "Nino isn't being very persuasive."
  },
  {
    "character": "一花",
    "japanese": "だね。",
    "translation": "Right?"
  },
  {
    "character": "二乃",
    "japanese": "なにか言ったかしらぁ？",
    "translation": "Did you say something?"
  },
  {
    "character": "一花",
    "japanese": "いえいえ、なんでも。",
    "translation": "No no, nothing."
  },
  {
    "character": "三玖",
    "japanese": "手荒じゃないなら、なにをするの？",
    "translation": "If you're not gonna be forceful,\nwhat are you gonna do?"
  },
  {
    "character": "二乃",
    "japanese": "そうねぇ。\n私たちがフー君とイチャイチャして見せて、\n四葉に危機感を持ってもらうとか、どう？",
    "translation": "Let's see.\nHow about we get all nice and close with Fu-kun,\nand make Yotsuba feel like she's in a crisis?"
  },
  {
    "character": "五月",
    "japanese": "ええっ！？",
    "translation": "Whaaat?!"
  },
  {
    "character": "三玖",
    "japanese": "それ、いい。\n明日からやろう。",
    "translation": "Good idea.\nLet's do it starting tomorrow."
  },
  {
    "character": "五月",
    "japanese": "えええええ！？",
    "translation": "EHHHHHH?!"
  },
  {
    "character": "二乃",
    "japanese": "あんたはどうするのよ、五月？",
    "translation": "What are you gonna do, Itsuki?"
  },
  {
    "character": "五月",
    "japanese": "私もですか！？\n私には……む、無理です……。",
    "translation": "Me?!\nI...c-can't do it..."
  },
  {
    "character": "二乃",
    "japanese": "まあ、そうよね。\nじゃあ私と三玖でやるわ。",
    "translation": "Yeah, figured.\nThen, Miku and I will do it."
  },
  {
    "character": "三玖",
    "japanese": "一花と五月は邪魔しないでくれればいい。",
    "translation": "Ichika, Itsuki, you don't need to bother us."
  },
  {
    "character": "一花",
    "japanese": "オッケー。\nでも、あんまり暴走しないようにね。",
    "translation": "Okay.\nBut, don't go too overboard, alright?"
  },
  {
    "character": "二乃",
    "japanese": "覚悟なさい、四葉。\n私は隙を見せたら奪うって言ったわよね？",
    "translation": "Get ready, Yotsuba.\nI said I would steal him if I saw a chance, didn't I?"
  },
  {
    "character": "三玖",
    "japanese": "絶対に背中を押してなんてあげないって\n言ったのは本気だから。",
    "translation": "I said I wouldn't 'push' them no matter what,\nand I meant it."
  },
  {
    "character": "一花",
    "japanese": "あ、聞いてない。",
    "translation": "Ooohh. I didn't hear that."
  },
  {
    "character": "五月",
    "japanese": "い、一花！\nこれは、さすがに止めないと！",
    "translation": "I-Ichika! I think we need to stop this now!"
  },
  {
    "character": "一花",
    "japanese": "んー……。",
    "translation": "Hm..."
  },
  {
    "character": "一花",
    "japanese": "実を言うとさ、あの２人はいつまで\nいまみたいな関係を続けるつもりなのかな、とは\n思っちゃうよね、やっぱり。",
    "translation": "To be honest, I wonder how long those two\nwill continue their relationship like this."
  },
  {
    "character": "五月",
    "japanese": "一花まで！？",
    "translation": "Even you think so, Ichika?!"
  },
  {
    "character": "一花",
    "japanese": "もちろん、それが悪いって言うつもりはないよ？\nでも五月ちゃんだって心の中では\nそう思ってるところ、ない？",
    "translation": "Of course, I don't mean to say that it's a bad thing.\nBut don't you think that\neven you feel that way deep down inside, Itsuki-chan?"
  },
  {
    "character": "五月",
    "japanese": "……いつまで敬語なのか、と\n四葉に言ってしまったことはあります。",
    "translation": "...I did ask Yotsuba once,\n'How long are you going to use polite language?'"
  },
  {
    "character": "五月",
    "japanese": "それに、四葉に対する彼の態度が\nあまり見えてこないのは、こちらとしても\nどこかモヤモヤしてしまって。",
    "translation": "Also, I can't really tell Uesugi-kun's attitude\ntowards Yotsuba, and it's bothering me."
  },
  {
    "character": "一花",
    "japanese": "うんうん、やっぱりそこだよね。\nフータロー君にもっと\n男らしさを見せて欲しいところでもあるわけ。",
    "translation": "Yeah, that's true.\nI'd also want to see more masculinity from Futaro-kun."
  },
  {
    "character": "らいは",
    "japanese": "お兄ちゃんは恋愛ベタだし、\n人とのコミュニケーションも下手だから。\n困っちゃうよ。",
    "translation": "Big bro is bad at communication\nand new at love,\nso it's pretty hard to deal with him, huh."
  },
  {
    "character": "一花",
    "japanese": "私たちとの付き合いで、\n大分マシになったとは思うけどね。",
    "translation": "I really do think he's gotten better with us, though."
  },
  {
    "character": "一花",
    "japanese": "一応、２人のためにはなりそうだからさ。\nここはひとまず見守って、\n事態がエスカレートしたら私たちで止めよう。",
    "translation": "Anyway, we should watch over them for now.\nIf things get worse, we'll step in."
  },
  {
    "character": "五月",
    "japanese": "……わかりました。\nしばらく見守ってみましょう。",
    "translation": "...Alright.\nLet's watch them for a while."
  },
  {
    "character": "らいは",
    "japanese": "あんなお兄ちゃんだけど、よろしくお願いします。",
    "translation": "My big bro is pretty dang weird,\nbut please take care of him."
  },
  {
    "character": "一花",
    "japanese": "それで、二乃？\n四葉に危機感を持ってもらうとしても、\nいつまでこの作戦をやるつもりなの？",
    "translation": "So, Nino? How long do you plan on doing this strategy,\neven if it means it makes Yotsuba feel bad?"
  },
  {
    "character": "二乃",
    "japanese": "そうね……。",
    "translation": "Well..."
  },
  {
    "character": "二乃",
    "japanese": "この旅行のあいだに、\nあの子がフー君に対して敬語をやめる――",
    "translation": "How about we make it a goal to have her\nstop using honorifics%p-2;――"
  },
  {
    "character": "二乃",
    "japanese": "もしくは名前で呼べたら合格ってことにして\n作戦も終わりにする、でどうかしら？",
    "translation": "Or, start calling Fu-kun by his name during this trip,\nand end the strategy there?"
  },
  {
    "character": "五月",
    "japanese": "やはり、その点は\nみんな気になっているのですね。",
    "translation": "It seems like everyone is worried about that."
  },
  {
    "character": "三玖",
    "japanese": "気になるよ。\nフータローが気にしてないのがおかしい。",
    "translation": "I'm worried too.\nIt's strange that Futaro\ndoesn't seem to be bothered by it."
  },
  {
    "character": "五月",
    "japanese": "ですが、この旅行中にクリアする課題としては\n少々難しすぎなのでは……。",
    "translation": "But isn't that goal too difficult to achieve\nduring this trip...?"
  },
  {
    "character": "二乃",
    "japanese": "だからって簡単な課題にしても意味ないでしょ。",
    "translation": "Well really, an easy goal would be meaningless,\nwouldn't it?"
  },
  {
    "character": "五月",
    "japanese": "……確かに。",
    "translation": "...Alright then."
  },
  {
    "character": "二乃",
    "japanese": "じゃあ決まりね！\n三玖、明日から実行よ！",
    "translation": "Okay, it's settled!\nMiku, the plan starts tomorrow!"
  },
  {
    "character": "三玖",
    "japanese": "了解。",
    "translation": "Roger."
  },
  {
    "character": "五月",
    "japanese": "四葉、頑張ってください。",
    "translation": "Do your best, Yotsuba."
  }
]