[
  {
    "character": "四葉",
    "japanese": "このお皿もいいかも。\nこの模様ってなにかの葉っぱかな？",
    "translation": "This plate looks nice too.\nI wonder if this pattern is some kind of leaf?"
  },
  {
    "character": "二乃",
    "japanese": "あら、いいじゃない。\n色合いが鮮やかだし、良い品だと思うわ。",
    "translation": "Oh, it's nice.\nThe color is vivid, and I think it's a good product."
  },
  {
    "character": "風太郎",
    "japanese": "よう、２人揃って買い物中か？",
    "translation": "Hey, are you two shopping together?"
  },
  {
    "character": "四葉",
    "japanese": "あっ、上杉さんもこっちに来たんですか？",
    "translation": "Oh, Uesugi-san, did you come over here too?"
  },
  {
    "character": "風太郎",
    "japanese": "ああ、なにか面白いものでも――",
    "translation": "Yeah, is there something interesting%p-2;――"
  },
  {
    "character": "二乃",
    "japanese": "フー君！",
    "translation": "Fu-kun!"
  },
  {
    "character": "風太郎",
    "japanese": "ぐはっ！？",
    "translation": "GUAAH?!"
  },
  {
    "character": "四葉",
    "japanese": "に、二乃！？",
    "translation": "N-Nino?!"
  },
  {
    "character": "二乃",
    "japanese": "ねえ、せっかく会えたんだから\n一緒に見て回りましょ？",
    "translation": "Hey, since we've run into each other and all that,\nlet's look around together, okay?"
  },
  {
    "character": "風太郎",
    "japanese": "だから、急にくっついて来るなって。\n危ないだろ。",
    "translation": "I said, don't suddenly stick to me like that.\nIt's dangerous, isn't it?"
  },
  {
    "character": "二乃",
    "japanese": "え～？\nだって、こうしてないと\nすぐにどこか行っちゃうでしょ？",
    "translation": "Awwww?\nBut if I don't,\nyou'll end up going somewhere else, right?"
  },
  {
    "character": "四葉",
    "japanese": "あ、あの、二乃？",
    "translation": "U-um, Nino?"
  },
  {
    "character": "二乃",
    "japanese": "なに？",
    "translation": "What?"
  },
  {
    "character": "四葉",
    "japanese": "ええっと……上杉さんも困ってるみたいだし、\nそれに、ちょっと……ね？",
    "translation": "Well... Uesugi-san seems to be having a hard time,\nand, I mean...like, you know?"
  },
  {
    "character": "二乃",
    "japanese": "ああ、そういうこと。",
    "translation": "Oh, I see."
  },
  {
    "character": "二乃",
    "japanese": "これは思い出作りの一環よ。\n親しい友達だったら、これくらい普通でしょ。",
    "translation": "This is part of the memory making process.\nIf you're close friends, this is normal."
  },
  {
    "character": "四葉",
    "japanese": "な、なるほど、そっか！\nそうだよね、普通だよね！",
    "translation": "I-I see, that's right!\nThis is normal, right?"
  },
  {
    "character": "二乃",
    "japanese": "そうそう、普通よ。\n四葉はちょっと考えすぎ。",
    "translation": "That's right, it's normal.\nYou're overthinking things, Yotsuba."
  },
  {
    "character": "風太郎",
    "japanese": "（俺も考えすぎなのか？\n　意識するあまり、また自意識過剰に――）",
    "translation": "(Am I thinking too much too?\n Am I becoming too self-conscious again%p-2;――%p;)"
  },
  {
    "character": "四葉",
    "japanese": "…………。",
    "translation": "......"
  },
  {
    "character": "風太郎",
    "japanese": "（いや、ここには四葉だっているんだぞ？\n　そして俺は四葉と……）",
    "translation": "(No, Yotsuba is here, I'm dating her...)"
  },
  {
    "character": "風太郎",
    "japanese": "二乃、ちょっと――",
    "translation": "Nino, wait a minute%p-2;――"
  },
  {
    "character": "二乃",
    "japanese": "ほら、フー君！　こっちこっち！",
    "translation": "Hey, Fu-kun! Here, come here!"
  },
  {
    "character": "風太郎",
    "japanese": "お、おい！　急に引っ張るな！",
    "translation": "H-hey! Don't pull me like that all of a sudden!"
  },
  {
    "character": "二乃",
    "japanese": "この辺りって焼き物のお店が多いのよ。\nいろんな食器が並んでて、見てるだけでも楽しいわ。",
    "translation": "There are a lot of pottery shops around here.\nThere are various dishes lined up,\nand it's fun just to look at them."
  },
  {
    "character": "風太郎",
    "japanese": "俺は食器を見て回るなんて初めての体験だが。",
    "translation": "This is the first time I've ever gone around\nlooking at dishes."
  },
  {
    "character": "二乃",
    "japanese": "どう？　気に入ったの、ある？",
    "translation": "So, do you like anything?"
  },
  {
    "character": "四葉",
    "japanese": "あの、上杉さん！\nこの『やちむん』ってなんですかね？",
    "translation": "Hey, Uesugi-san! What is this 'yachimun'?"
  },
  {
    "character": "風太郎",
    "japanese": "ああ、確か沖縄の言葉で焼き物のことだ。",
    "translation": "Ah, that's a word in the Okinawan dialect\nthat means pottery."
  },
  {
    "character": "四葉",
    "japanese": "おお、そうなんですね。\nさすがです。",
    "translation": "Oh, I see.\nYou know so much."
  },
  {
    "character": "風太郎",
    "japanese": "通り沿いに陶器所なんかもあったし、\n探せば、陶芸体験もできるんじゃないか？",
    "translation": "There are also pottery studios along the street,\nso if you look for them,\nyou can try pottery making, right?"
  },
  {
    "character": "四葉",
    "japanese": "へぇ～、それはちょっと面白そうです。",
    "translation": "Wow, that sounds interesting."
  },
  {
    "character": "二乃",
    "japanese": "ふーん……。",
    "translation": "Hmmm..."
  },
  {
    "character": "風太郎",
    "japanese": "うん？　どうかしたのか？",
    "translation": "Mmm? What's the matter?"
  },
  {
    "character": "二乃",
    "japanese": "なんでもない。\nそれより、お皿を見て回りましょ。\n何枚か新しいのが欲しかったのよ。",
    "translation": "It's nothing. Anyway, let's look at the plates.\nI wanted to get some new ones."
  },
  {
    "character": "四葉",
    "japanese": "あ、そうだったね。\n気に入ったの見つかった？",
    "translation": "Oh, right. Did you find some you like?"
  },
  {
    "character": "二乃",
    "japanese": "んー、逆に、良い物が多くて困ってる感じ。\nどう選ぼうかしら。",
    "translation": "Hmm, actually, there are too many good things,\nand I'm having trouble making a decision."
  },
  {
    "character": "四葉",
    "japanese": "やっぱり沖縄っぽいのがいいかも。\nほら、この青なんて海っぽいし、\nこっちのは南国の浜辺っぽいよ。",
    "translation": "Maybe something that looks like it's Okinawa-ish\nwould be good. Like this blue one that's kinda sea-ish,\nor this one that's all tropical beach-ish."
  },
  {
    "character": "風太郎",
    "japanese": "お前、ぽいぽいばっかだな。",
    "translation": "What's with all the 'ish'?"
  },
  {
    "character": "四葉",
    "japanese": "えへへ～。\n上手く伝えられなくてすみません。",
    "translation": "Ehehe.\nSorry I can't express myself very well."
  },
  {
    "character": "二乃",
    "japanese": "でも、食器を選ぶ時にはそういう感覚も大切よ？",
    "translation": "But, when choosing what to eat,\nthat kind of feeling is also important, you know?"
  },
  {
    "character": "風太郎",
    "japanese": "感覚が？　なんでだ？",
    "translation": "That feeling? What do you mean?"
  },
  {
    "character": "二乃",
    "japanese": "料理は舌だけじゃなくて、目でも味わうものなの。\n同じ料理でも、盛り付ける食器によって\n印象が変わるわ。",
    "translation": "Cooking isn't just about taste, it's also about savoring\nthe dish with your eyes. Even the same dish can give\na different impression depending on what it's served in."
  },
  {
    "character": "二乃",
    "japanese": "フー君が気が付かなくても、\nお互いが相手の魅力を引き立てあってるのよ。",
    "translation": "Even if you don't notice it,\nwe're both bringing out each other's charms."
  },
  {
    "character": "風太郎",
    "japanese": "まあ、言いたいことはわかるが……。",
    "translation": "Well, I can see what you're trying to say..."
  },
  {
    "character": "二乃",
    "japanese": "ねぇ、フー君？",
    "translation": "Hey, Fu-kun?"
  },
  {
    "character": "四葉",
    "japanese": "えっ！？",
    "translation": "HUH?!"
  },
  {
    "character": "二乃",
    "japanese": "私がフー君の魅力を引き出してあげてもいいのよ？\nその代わり、フー君は私の魅力を――",
    "translation": "I can bring out your charm, you know, Fu-kun?\nIn exchange, Fu-kun, bring out mine%p-2;――"
  },
  {
    "character": "四葉",
    "japanese": "に、二乃！\nちょっと……！",
    "translation": "N-Nino!\nHold on!"
  },
  {
    "character": "二乃",
    "japanese": "なに、四葉。",
    "translation": "What, Yotsuba."
  },
  {
    "character": "風太郎",
    "japanese": "（なんなんだよ。\n　二乃のやつ、急に積極的になって……。\n　いまのはさすがに俺の勘違いってわけじゃないだろ）",
    "translation": "(What's going on?\n Nino suddenly got so aggressive...\n It can't be just my imagination, though, can it?)"
  },
  {
    "character": "四葉",
    "japanese": "これ！\nこのお皿、二乃の好みだと思うんだけどどうかな？",
    "translation": "This!\nHow about this dish? I think it suits your taste, Nino."
  },
  {
    "character": "二乃",
    "japanese": "あっ！　いいじゃない！",
    "translation": "Ah! How nice!"
  },
  {
    "character": "二乃",
    "japanese": "これって種類も色々あるのね。\n大皿から一通り揃えられそうだわ。",
    "translation": "There are various types of these dishes, aren't there?\nSeems you can collect them in a set\nfrom large plates to small ones."
  },
  {
    "character": "風太郎",
    "japanese": "そんなに必要ないだろ？\n何枚選ぶつもりなんだ。",
    "translation": "You don't need those, right?\nHow many were you planning on buying?"
  },
  {
    "character": "二乃",
    "japanese": "だから、気分や料理に合わせようと思ったら\nいくらあってもいいものなのよ。",
    "translation": "Well, if you want to match your mood to the dish,\nyou can never have too many."
  },
  {
    "character": "四葉",
    "japanese": "二乃はホントにお皿にもこだわるもんねー。\nでも、確かに料理に合ってる食器だと\n食欲が増す気がするよ。",
    "translation": "Nino really pays attention to her dishes.\nBut, I do feel like my appetite increases\nwhen the tableware matches the food."
  },
  {
    "character": "風太郎",
    "japanese": "そんなに選んだら、持って帰るのが大変じゃないか？\nいったんホテルに預けるとしても、\n割れ物は運ぶのに気を遣うぞ。",
    "translation": "If you choose that many of them, won't it be difficult\nto take them home? Even if you leave them at the hotel,\nyou have to be careful when transporting fragile items."
  },
  {
    "character": "四葉",
    "japanese": "あ、そうですね。\nせっかく買ったのに\n途中で割れちゃったら悲しいです。",
    "translation": "Oh, yeah. That's true.\nIt would be sad if we bought them\nand they broke on the way back."
  },
  {
    "character": "二乃",
    "japanese": "あんたは荷物を雑に扱いすぎなのよ。",
    "translation": "You're too rough with your luggage."
  },
  {
    "character": "二乃",
    "japanese": "ていうか、配送サービスくらいあるでしょ。\nそれでマンションまで送ってもらえば問題ないわ。",
    "translation": "Either way, there are delivery services, right?\nWe can just have them delivered\nto our apartment."
  },
  {
    "character": "四葉",
    "japanese": "あ、そっか。\n自分で持って帰る必要はないね。",
    "translation": "Oh, right.\nWe don't have to carry them ourselves."
  },
  {
    "character": "風太郎",
    "japanese": "ここは沖縄だぞ？\n配送料が馬鹿にならないだろ。",
    "translation": "This is Okinawa, you know?\nThe shipping costs would be ridiculous."
  },
  {
    "character": "二乃",
    "japanese": "それくらい、今回の旅費に比べたら\n誤差の範囲にも入らないわよ？",
    "translation": "Well, compared to our travel expenses this time,\nit's still under budget for a normal trip."
  },
  {
    "character": "風太郎",
    "japanese": "（ぐっ……これが住む世界の違いってやつか！？）",
    "translation": "(Grr... Is this the difference\n in the worlds we live in?!)"
  },
  {
    "character": "風太郎",
    "japanese": "お前が気に入ったのがあるなら、\n将来、揃えてみたらどうだ？",
    "translation": "If you find something you like,\nhow about getting a whole set in the future?"
  },
  {
    "character": "四葉",
    "japanese": "えっ？",
    "translation": "Huh?"
  },
  {
    "character": "二乃",
    "japanese": "将来って……！",
    "translation": "In the future?!"
  },
  {
    "character": "二乃",
    "japanese": "もう、フー君ったら、\nそんな先のことまで考えちゃってるなんて。",
    "translation": "Oh my GOODNESS, Fu-kun.\nYou're already thinking that far ahead."
  },
  {
    "character": "風太郎",
    "japanese": "別におかしくないだろ。\nしっかり考えておかないとな。",
    "translation": "It's not that strange.\nYou have to think ahead and be prepared."
  },
  {
    "character": "四葉",
    "japanese": "う、上杉さん？",
    "translation": "U-Uesugi-san?"
  },
  {
    "character": "風太郎",
    "japanese": "二乃は自分の店を出すのが夢なんだろ？\nその時のことを考えて、いまから準備をしておくのは\n悪くないと思うぞ。",
    "translation": "Your dream is to open your own place, right, Nino?\nIt's not a bad idea to prepare for it now\nby thinking ahead."
  },
  {
    "character": "二乃",
    "japanese": "あ……。\nそっちね、そうよね。",
    "translation": "Ah...\nThat's what you meant. I see."
  },
  {
    "character": "四葉",
    "japanese": "はぁ～……。",
    "translation": "*sigh*"
  },
  {
    "character": "風太郎",
    "japanese": "なんだ、どうしたんだ？",
    "translation": "What? What's wrong?"
  },
  {
    "character": "二乃",
    "japanese": "なんでもないわよ。",
    "translation": "It's nothing."
  },
  {
    "character": "二乃",
    "japanese": "けど、フー君が覚えててくれたんだし……\nそれはそれでありかしらね。",
    "translation": "But, you remembered that much, Fu-kun...\nThat's quite considerate of you, right?"
  },
  {
    "character": "二乃",
    "japanese": "ひとまず、こんなところかしら。\n後は送ってもらえばいいだけね。",
    "translation": "Well okay, I think this is about it for now.\nWe just need to have them delivered to us."
  },
  {
    "character": "風太郎",
    "japanese": "思ったより少ないな。\nさっきの勢いからして全種類買うのかと思ったが。",
    "translation": "Oh, you bought fewer than I expected.\nConsidering how enthusiastic you were earlier,\nI thought you were going to buy out everything."
  },
  {
    "character": "二乃",
    "japanese": "本当ならそうしたいけど、\nこれ以上、食器が増えると\n置き場所に困ることを思い出したのよ。",
    "translation": "I really want to, but if I get any more tableware,\nI'll start having trouble finding places to put it."
  },
  {
    "character": "風太郎",
    "japanese": "ええー……。\nどんだけあるんだよ……。",
    "translation": "Huhh...\nJust how many dishes do you have...?"
  }
]