[
  {
    "character": "五月",
    "japanese": "…………。",
    "translation": "......"
  },
  {
    "character": "四葉",
    "japanese": "五月、見ーつけた！\n捜しちゃったよ。",
    "translation": "Itsuki, I found you!\nI was looking for you."
  },
  {
    "character": "五月",
    "japanese": "四葉？\n……あなた１人ですか？",
    "translation": "Yotsuba?\n...Are you alone?"
  },
  {
    "character": "四葉",
    "japanese": "うん。\n五月と２人で話がしたくて。",
    "translation": "Yeah.\nI wanted to talk with you, Itsuki."
  },
  {
    "character": "五月",
    "japanese": "え？　なんです？",
    "translation": "Huh? What is it?"
  },
  {
    "character": "四葉",
    "japanese": "五月は、どうして急に\n五つ子ゲームをやろうなんて言い出したの？",
    "translation": "Why did you suddenly suggest\nwe play the quintuplets game?"
  },
  {
    "character": "五月",
    "japanese": "！……",
    "translation": "!..."
  },
  {
    "character": "五月",
    "japanese": "それは……上杉君への試練として……。",
    "translation": "Well... As a test for Uesugi-kun..."
  },
  {
    "character": "四葉",
    "japanese": "ホントにそれだけ？",
    "translation": "Is that really it?"
  },
  {
    "character": "五月",
    "japanese": "…………。",
    "translation": "......"
  },
  {
    "character": "四葉",
    "japanese": "多分だけど、私に関係があるんじゃない？\n……京都でのこと？",
    "translation": "I'm just guessing, but could it \nhave something to do with me?\n...About what happened in Kyoto?"
  },
  {
    "character": "五月",
    "japanese": "…………。",
    "translation": "......"
  },
  {
    "character": "五月",
    "japanese": "ええ。\nあなたの推測通りです。",
    "translation": "Yes.\nIt's just as you guessed."
  },
  {
    "character": "四葉",
    "japanese": "やっぱり、そっか。",
    "translation": "I knew it."
  },
  {
    "character": "五月",
    "japanese": "ですが、上杉君に対する試練というのも本心です。\n彼の優柔不断さを正すには、これくらいは\n必要だと思っていましたから。",
    "translation": "But also, testing Uesugi-kun was my true intention.\nI thought it was necessary\nto correct his indecisiveness."
  },
  {
    "character": "五月",
    "japanese": "ただ、この様な形にすれば……\nあなたも昔のことを伝えやすくなるかも\nしれないと……。",
    "translation": "However, if we do it in this way...\nIt might also make it easier\nfor you to talk about the past..."
  },
  {
    "character": "四葉",
    "japanese": "…………。",
    "translation": "......"
  },
  {
    "character": "五月",
    "japanese": "四葉。\n私は、あなたのためにも――",
    "translation": "Yotsuba.\nFor your sake, too%p-2;――"
  },
  {
    "character": "五月",
    "japanese": "６年前、京都で会った子はあなただったと\n上杉君に知ってほしいのです。",
    "translation": "I want Uesugi-kun to know\nthat the child he met in Kyoto six years ago\nwas you."
  },
  {
    "character": "四葉",
    "japanese": "ありがと。\n私のこと、そんなに考えてくれてたんだね。",
    "translation": "Thank you.\nYou were really thinking about me that much, huh?"
  },
  {
    "character": "四葉",
    "japanese": "でも、それはもういいんだ。\n私、過去の思い出には頼らないって決めたから。",
    "translation": "But, that's okay now.\nI've decided not to rely on past memories anymore."
  },
  {
    "character": "五月",
    "japanese": "ですが！\nあなたは本当にこのままでいいのですか？\nもう、これが最後なのかもしれないのですよ！？",
    "translation": "But!\nIs it really okay to leave it like that?\nThis might be the last chance you have, you know?!"
  },
  {
    "character": "四葉",
    "japanese": "五月……。",
    "translation": "Itsuki..."
  },
  {
    "character": "五月",
    "japanese": "……このゲームなら全員が平等です。",
    "translation": "...With this game, all of us are equal."
  },
  {
    "character": "五月",
    "japanese": "二乃、三玖、それに一花も。\n他のみんなが上杉君に答えを求めているのなら――",
    "translation": "Nino, Miku, and Ichika too.\nIf everyone else is looking for an answer\nfrom Uesugi-kun%p-2;――"
  },
  {
    "character": "五月",
    "japanese": "あなたにだって\n同じように機会があるべきなんです。",
    "translation": "You deserve the same opportunity. "
  },
  {
    "character": "四葉",
    "japanese": "…………。",
    "translation": "......"
  },
  {
    "character": "五月",
    "japanese": "過去の思い出には頼らないと言っても、\nあなたはいまだって、彼のことが……。",
    "translation": "Even though you say\nyou don't rely on memories of the past,\nyou still think about him..."
  },
  {
    "character": "四葉",
    "japanese": "ごめんね。\n五月にはいつも、つらい役ばかりやらせちゃって。",
    "translation": "I'm sorry.\nI always make you play the difficult roles, Itsuki."
  },
  {
    "character": "四葉",
    "japanese": "全部、私の過去に巻き込んじゃったせいだよね。",
    "translation": "It's all because I got you involved in my past."
  },
  {
    "character": "五月",
    "japanese": "私のことは構いません！\nそれよりもいまは、あなたの――",
    "translation": "Don't mind me!\nRight now, it's about you%p-2;――"
  },
  {
    "character": "四葉",
    "japanese": "でも、五月はちょっとだけ勘違いしてるかも。",
    "translation": "However, you might be misunderstanding things a bit."
  },
  {
    "character": "五月",
    "japanese": "……どういう、ことですか？",
    "translation": "...What do you mean?"
  },
  {
    "character": "四葉",
    "japanese": "いまの私は、過去とか関係なく\n上杉さんのことが好きなんだ。",
    "translation": "Right now, I like Uesugi-san,\nregardless of the past or anything else."
  },
  {
    "character": "五月",
    "japanese": "！……",
    "translation": "!..."
  },
  {
    "character": "四葉",
    "japanese": "だから、もう過去には頼らない。\n五月にもそれをわかってほしい。",
    "translation": "That's why I won't rely on the past anymore.\nI want you to understand that too, Itsuki."
  },
  {
    "character": "五月",
    "japanese": "それは……。",
    "translation": "That's..."
  },
  {
    "character": "四葉",
    "japanese": "もう、心配しなくても大丈夫ってこと。",
    "translation": "You don't have to worry about me anymore."
  },
  {
    "character": "四葉",
    "japanese": "学園祭で色々あったよね。\nあの時に私も、一歩踏み出したんだ。",
    "translation": "A lot happened at the school festival, didn't it?\nThat was when I took a step forward too."
  },
  {
    "character": "四葉",
    "japanese": "昔のことより大切なのはいま。",
    "translation": "What's important is now, not the past."
  },
  {
    "character": "四葉",
    "japanese": "いつまでも過去の思い出に頼っていないで、\nいまの自分の価値を探そうって、前に進んだ。",
    "translation": "I moved forward, forever not relying on my memories\nof the past, to find my own value in the present."
  },
  {
    "character": "五月",
    "japanese": "大切なのはいま……。",
    "translation": "What's important, is now..."
  },
  {
    "character": "四葉",
    "japanese": "うん。\nそれからはずっと、いまの私として\n上杉さんと接してきたんだ。",
    "translation": "Yeah. Since then,\nI've been interacting with Uesugi-san as who I am now."
  },
  {
    "character": "四葉",
    "japanese": "それでね、思ったんだよ。",
    "translation": "So, I thought about it."
  },
  {
    "character": "四葉",
    "japanese": "やっぱり私は\n上杉さんのことが好きなんだな……って。",
    "translation": "I realized,\nI really do like him..."
  },
  {
    "character": "四葉",
    "japanese": "だから――",
    "translation": "So%p-2;―――"
  },
  {
    "character": "四葉",
    "japanese": "多分、あり得ないとは思うけど、\nもし上杉さんが私のことを選んでくれたなら……。",
    "translation": "I know it's probably impossible,\nbut if Uesugi-san were to choose me..."
  },
  {
    "character": "五月",
    "japanese": "四葉、あなた……。",
    "translation": "Yotsuba, you..."
  },
  {
    "character": "四葉",
    "japanese": "……うん。",
    "translation": "Yeah."
  },
  {
    "character": "五月",
    "japanese": "…………。",
    "translation": "......"
  },
  {
    "character": "五月",
    "japanese": "（四葉にとって、\n　もはや過去はこだわるべき事柄ではないのですね。\n　それなのに私ばかりが……）",
    "translation": "(For Yotsuba,\n the past is no longer something to cling to.\n And yet, why am I the only one, who...)"
  },
  {
    "character": "四葉",
    "japanese": "ねえ、五月。\n私は五月自身にも、\n自分の気持ちをちゃんと考えてほしいんだ。",
    "translation": "Hey, Itsuki. I want you to think carefully\nabout your own feelings too."
  },
  {
    "character": "五月",
    "japanese": "えっ……。",
    "translation": "Huh..."
  },
  {
    "character": "四葉",
    "japanese": "五月が自分で言ってたよ？\nこの五つ子ゲームでは全員が平等だって。",
    "translation": "You said it yourself, didn't you?\nIn this quintuplets game, everyone is equal."
  },
  {
    "character": "四葉",
    "japanese": "もし上杉さんが五月を選んでくれたら、\n五月はそれにどう応えるの？",
    "translation": "If Uesugi-san chose you, Itsuki,\nhow would you respond?"
  },
  {
    "character": "五月",
    "japanese": "そ、それは……。",
    "translation": "W-well..."
  },
  {
    "character": "四葉",
    "japanese": "ね？　ちゃんと考えておかないと。",
    "translation": "Right? You've gotta think about that."
  },
  {
    "character": "五月",
    "japanese": "（……それは、学園祭の時にも考えさせられたこと）",
    "translation": "(That's something I was forced to think about\n during the school festival.)"
  },
  {
    "character": "五月",
    "japanese": "（だけど結果的に彼は誰も選ばず、\n　私の……私の姉たちの覚悟をふいにした）",
    "translation": "(But in the end, Uesugi-kun didn't choose anyone,\n and disregarded my...or rather, our resolve.)"
  },
  {
    "character": "五月",
    "japanese": "（その答えに私たちは当然憤った。\n　憤ったけれど……心のどこかで、私は……）",
    "translation": "(We naturally felt indignant at that answer.\n We felt indignant, but...\n somewhere deep in my heart, I...)"
  },
  {
    "character": "五月",
    "japanese": "…………。",
    "translation": "......"
  },
  {
    "character": "五月",
    "japanese": "（……そうだったのですね）",
    "translation": "(...So, that's how I truly felt.)"
  },
  {
    "character": "五月",
    "japanese": "（私は、怖かった。\n　他のみんなのような覚悟すらできていない自分が、\n　もしも選ばれたりしたら……）",
    "translation": "(I was scared. I, who couldn't even muster\n the same resolve as everyone else,\n if by some chance I were chosen...)"
  },
  {
    "character": "五月",
    "japanese": "（私が選ばれるということは、\n　他のみんなが選ばれないということ）",
    "translation": "(For me to be chosen, means that none of the others\n will be chosen.)"
  },
  {
    "character": "五月",
    "japanese": "（きっと、そこから逃げ出したくて……\n　姉妹の平穏や四葉のことを理由にして……）",
    "translation": "(I probably wanted to run away from there...\n using the peace of my sisters and Yotsuba\n as an excuse...)"
  },
  {
    "character": "五月",
    "japanese": "…………。",
    "translation": "......"
  },
  {
    "character": "五月",
    "japanese": "（彼に覚悟を求めておきながら、\n　私は自分が覚悟することを拒否し……\n　あまつさえ、その苛立ちを彼へぶつけてしまった）",
    "translation": "(While demanding resolve from him,\n I refused to have any resolve of my own...\n and even vented my frustration onto him.)"
  },
  {
    "character": "五月",
    "japanese": "（あの時の言葉は、\n　私の、私自身への言葉だった……）",
    "translation": "(Those words at that time\n were words meant for myself...)"
  },
  {
    "character": "四葉",
    "japanese": "五月？　大丈夫？",
    "translation": "Itsuki? Are you alright?"
  },
  {
    "character": "五月",
    "japanese": "……私も、もう覚悟を決めないといけないのですね。",
    "translation": "...I also need to make up my mind."
  },
  {
    "character": "四葉",
    "japanese": "うん、そうだよ。\n私たち、みんなのためにも。",
    "translation": "Yeah, that's right. For everyone's sake."
  },
  {
    "character": "五月",
    "japanese": "覚悟を決めるというのは、\nこんなにも怖いものだなんて……。",
    "translation": "Making up one's mind is such a frightening thing..."
  },
  {
    "character": "四葉",
    "japanese": "うん、すっごく勇気がいるでしょ？",
    "translation": "Yeah, it takes a lot of courage, doesn't it?"
  },
  {
    "character": "五月",
    "japanese": "私、上杉君にひどいことをしてしまいました。\n彼に謝らなければ……。",
    "translation": "I was so awful to Uesugi-kun.\nI need to apologize to him..."
  },
  {
    "character": "四葉",
    "japanese": "……不思議だよね。\n恋をすると、自分の気持ちすら\nままならなくなっちゃうんだ。",
    "translation": "...It's strange, isn't it?\nWhen you fall in love,\neven your own feelings become uncontrollable."
  },
  {
    "character": "五月",
    "japanese": "こ、恋と言うか……。\nまだ私は自分自身の気持ちの整理すら……。",
    "translation": "W-well, it's not exactly love...\nI haven't even sorted out my own feelings yet..."
  },
  {
    "character": "四葉",
    "japanese": "ちゃんと考えよう。\nまだ、ちょっとだけ時間は残ってるんだし。",
    "translation": "Let's think it through.\nWe still have a little time left."
  },
  {
    "character": "五月",
    "japanese": "そうですね……。",
    "translation": "That's true..."
  },
  {
    "character": "五月",
    "japanese": "四葉、すみませんでした。\nあなたにも余計な心配をかけてしまって。",
    "translation": "Yotsuba, I'm sorry.\nI made you worry unnecessarily."
  },
  {
    "character": "四葉",
    "japanese": "いいのいいの。\n妹は、お姉ちゃんに迷惑をかけるものなんだから。",
    "translation": "It's okay, it's okay.\nLittle sisters\nare supposed to trouble their big sisters."
  },
  {
    "character": "四葉",
    "japanese": "むしろ私のほうが謝らないと。\n五月には散々、迷惑かけちゃったし……ごめんね。\n私、お姉ちゃんなのに。",
    "translation": "If anything, I should be the one apologizing.\nI caused you so much trouble, Itsuki...\nI'm sorry. Even though I'm your big sister."
  },
  {
    "character": "五月",
    "japanese": "いいんです。\n妹だって、姉を支えたいと思うものなんですよ。",
    "translation": "It's totally fine.\nUs little sisters too,\nwe want to support our big sisters."
  },
  {
    "character": "四葉",
    "japanese": "えへへ。\n持ちつ持たれつってやつかな？",
    "translation": "Hehe. It's a give-and-take relationship, right?"
  },
  {
    "character": "五月",
    "japanese": "それが……私たち姉妹のあり方ですから。",
    "translation": "That's...how we do things as sisters, after all."
  }
]