[
  {
    "message": "………………"
  },
  {
    "message": "…………"
  },
  {
    "message": "……"
  },
  {
    "message": "そして、翌日――"
  },
  {
    "name": "母",
    "message": "「じゃあ、お父さんと町内会の集まりに言ってくるから、\r\nお留守番よろしくね？」"
  },
  {
    "name": "美羽",
    "message": "「うん。いってらっしゃい」"
  },
  {
    "message": "そうして、お父さんとお母さんが出かけていく。"
  },
  {
    "message": "すると、すぐにお姉ちゃんが僕に抱きついてきてくれた。"
  },
  {
    "name": "美羽",
    "message": "「ゆ～うくんっ！」"
  },
  {
    "name": "優",
    "message": "「わわっ！？」"
  },
  {
    "name": "美羽",
    "message": "「邪魔者は行っちゃったし、エッチしよ？」"
  },
  {
    "name": "美羽",
    "message": "「今日はどうしよっか？　そろそろ変なこともしてみる？\r\nふふっ、ゆうくんのこと縛ってあげよっか？」"
  },
  {
    "message": "お姉ちゃんが無邪気にそう誘ってきてくれる。\r\nエ、エッチはしたいけど……！！"
  },
  {
    "name": "優",
    "message": "「ごめんっ！　しばらくお姉ちゃんとはエッチできないっ！」"
  },
  {
    "name": "美羽",
    "message": "「えっ？　ど、どうして？\r\n縛るっていうのは半分冗談――」"
  },
  {
    "name": "優",
    "message": "「ゆ、夢があるんだっ！　どうしても叶えたい夢がっ！\r\nその夢のために、今はエッチできなくて……！」"
  },
  {
    "name": "美羽",
    "message": "「夢？　どんな夢なの？」"
  },
  {
    "name": "優",
    "message": "「そ、それも今は教えられなくて……！\r\nでも、その……！　いつかちゃんと言うから……！」"
  },
  {
    "name": "美羽",
    "message": "「だけど、せっかく二人きりなのに――」"
  },
  {
    "name": "優",
    "message": "「～～っっ！　とにかく、ごめんっ！」"
  },
  {
    "name": "美羽",
    "message": "「あっ、待ってよっ！　ゆうくんっ、ゆうく～んっ！？\r\nそれならせめて、一緒に遊ぼうよ～！？」"
  },
  {
    "message": "お姉ちゃんの呼びかけを振り切って僕は走る。"
  },
  {
    "message": "ごめん、お姉ちゃん……！"
  },
  {
    "message": "でも、お姉ちゃんが魅力的過ぎて、\r\n一緒にいるだけで射精しちゃいそうになるんだ……！"
  },
  {
    "message": "ちょっとでも出しちゃったら、\r\nそれはもう全力全開の精子にならないっ……！"
  },
  {
    "message": "だから――ごめんっ！"
  },
  {
    "name": "美羽",
    "message": "「……ホントに行っちゃった。\r\nゆうくんったら、急にどうしちゃったんだろ」"
  },
  {
    "name": "美羽",
    "message": "「夢があるって言ってたけど……一体どんな夢なんだろ？\r\nしばらくエッチもできないって言ってたし……」"
  },
  {
    "name": "美羽",
    "message": "「でも、あの様子……エッチ自体はしたくないわけじゃ\r\nなさそうだったよね。無理やり我慢してるみたいだった」"
  },
  {
    "name": "美羽",
    "message": "「だったら――ふふっ。やることは一つ、かな」"
  },
  {
    "name": "優",
    "message": "「ふぅ……。やっと宿題終わった……」"
  },
  {
    "message": "残っていた春休みの宿題を片付ける頃には、\r\n窓の外はオレンジ色に染まり始めていた。"
  },
  {
    "message": "オナ禁するって決めて、雑念を全部振り払ったからかな。\r\n今までの人生で一番集中できた時間だったかも……。"
  },
  {
    "message": "よーしっ！　この調子で精子をしっかり溜めて、\r\nお姉ちゃんの危険日に備えるんだっ！"
  },
  {
    "name": "優",
    "message": "「ん？　あ、お姉ちゃんからだ……」"
  },
  {
    "message": "……もしかして、エッチのお誘いかな。\r\nだとしたら、ちゃんと断らないと……！"
  },
  {
    "message": "どんな魅力的な誘い文句でも断る――\r\nその決意を胸に僕はアプリを起動した。"
  },
  {
    "message": "起動したんだけど――"
  },
  {
    "name": "優",
    "message": "「――ひぃあっ！！？」"
  },
  {
    "message": "こ――これっ、またっ！？\r\nなんのメッセージもなく、ド直球でっ！？"
  },
  {
    "message": "わっ、わわっ！？　次々と送られてくる……！！"
  },
  {
    "message": "お姉ちゃんってば、完全に――"
  },
  {
    "name": "優",
    "message": "「っっ～～！！」"
  },
  {
    "message": "完全に、僕をムラムラさせるつもりだ……！！"
  },
  {
    "message": "『今はダメっ！』と返信しても、\r\n次から次へと無言で写真が送り続けられる。"
  },
  {
    "message": "こ、こうなったら、直接言いに行かなきゃ……！"
  },
  {
    "name": "優",
    "message": "「お姉ちゃんっ！　ああいうのを送るのはやめ――」"
  },
  {
    "name": "優",
    "message": "「――でっ！？」"
  },
  {
    "message": "リビングを開けた途端、セクシーな格好で\r\nマニキュアを塗るお姉ちゃんの姿が目に入ってくる。"
  },
  {
    "message": "こ、これ、この前のヤツだ……！\r\n僕が「エッチしたい」って言えるか試してきた時の……！"
  },
  {
    "message": "僕が直接言いに来ることを見越しての\r\nまさかの二段構えなんて……！！"
  },
  {
    "name": "美羽",
    "message": "「あ、ゆうくん。ふふっ、どうしたの？」"
  },
  {
    "name": "優",
    "message": "「ど、どうしたって……！」"
  },
  {
    "message": "落ち着け僕……！　ここで慌てちゃダメだ……。\r\nエッチなことを考えちゃえば、お姉ちゃんの思うつぼだ。"
  },
  {
    "message": "きっとお姉ちゃんは僕に押し倒させようとしてる。\r\n僕が実はエッチしたいってことを見抜いてる……！"
  },
  {
    "message": "でも、ここで飛びついちゃったら意味がない。\r\n僕のお姉ちゃん孕ませ計画が水の泡になってしまう……！"
  },
  {
    "message": "それだけは――避けなきゃ！！"
  },
  {
    "name": "優",
    "message": "「か、風邪……！」"
  },
  {
    "name": "美羽",
    "message": "「へ？　風邪？」"
  },
  {
    "name": "優",
    "message": "「そ、そんな格好してたら、風邪引いちゃうよっ？」"
  },
  {
    "name": "美羽",
    "message": "「……えと。ゆうくん？」"
  },
  {
    "name": "優",
    "message": "「そ、それだけっ！　あとエッチな写真送るの禁止っ！」"
  },
  {
    "message": "きっぱりと言うと、僕は回れ右をして走り出す。"
  },
  {
    "name": "美羽",
    "message": "「ちょ――ゆうくんっ！？」"
  },
  {
    "message": "ごめんっ、お姉ちゃん……！"
  },
  {
    "message": "何を言われても、どう誘惑されても、\r\nなびくわけにはいかないんだっ……！"
  },
  {
    "message": "でも、しばらくの辛抱だからっ。\r\n危険日になったら全部爆発させるからっ。"
  },
  {
    "message": "――心の中でお姉ちゃんに謝りながら部屋へと走る。\r\n半分起っきしてしまったちんちんを必死で沈めながら――"
  },
  {
    "name": "美羽",
    "message": "「……ゆうくん。本当に私とエッチするつもりないんだ……」"
  },
  {
    "name": "美羽",
    "message": "「ふんだ。いいよ、ゆうくんがその気なら\r\nトコトン誘惑して我慢できなくさせてあげるから」"
  },
  {
    "name": "美羽",
    "message": "「散々ムラムラさせて、たくさん焦らしてあげる。\r\n『エッチさせて』って泣いて謝らせてあげるもん……！」"
  },
  {
    "message": "………………"
  },
  {
    "message": "…………"
  },
  {
    "message": "……"
  },
  {
    "message": "その日からというもの――"
  },
  {
    "name": "優",
    "message": "「ふぁ……。おはよう……」"
  },
  {
    "name": "美羽",
    "message": "「あ。おはよう、ゆうくん。\r\n早起きできてえらいね？」"
  },
  {
    "name": "優",
    "message": "「うん……。今日から学園だから――って゛！？」"
  },
  {
    "name": "美羽",
    "message": "「ふふっ、そっか。春休みも終わりなんだ？」"
  },
  {
    "message": "お姉ちゃんがバスタオル一枚姿で、\r\nソファーに座り込んでいる。"
  },
  {
    "name": "優",
    "message": "「な――何してるの、お姉ちゃんっ！？\r\nそそそ、そんな格好、お母さんたちに見られたら……！！」"
  },
  {
    "name": "美羽",
    "message": "「大丈夫だよ。お母さんたち、\r\nまだまだ起きてこないだろうし」"
  },
  {
    "name": "優",
    "message": "「でも、いつもこの時間には――」"
  },
  {
    "message": "――あ、あれ？　起きてるはずだよね……？\r\n最初に起きて、朝食の準備してくれてるし……。"
  },
  {
    "name": "美羽",
    "message": "「今日の朝食は私が作るって言っておいたの。\r\nあと、ゆうくんの目覚まし時計、二時間早めておいたし」"
  },
  {
    "name": "優",
    "message": "「へっ！？　ホ、ホントだ、いま五時だし……！！\r\nいつの間に僕の目覚まし弄ったの……！？」"
  },
  {
    "name": "美羽",
    "message": "「細かいコトはいいじゃない。そ・れ・よ・り、\r\nあと二時間はお母さんたち起きてこないよ？」"
  },
  {
    "name": "優",
    "message": "「ふぇっ……！？」"
  },
  {
    "name": "美羽",
    "message": "「どうする？」"
  },
  {
    "name": "優",
    "message": "「ど、どうするって……」"
  },
  {
    "message": "お風呂上がりの熱気をまとったまま、\r\n肌を赤く火照らせてお姉ちゃんが微笑みかけてくる。"
  },
  {
    "message": "その悪戯っぽい笑みと色っぽい姿を見て、\r\n胸がドキンと弾んでしまうけれど――"
  },
  {
    "name": "優",
    "message": "「し、七時まで寝直してくるっ！！」"
  },
  {
    "name": "美羽",
    "message": "「あっ、ゆうくんっ！　……強情なんだから」"
  },
  {
    "name": "美羽",
    "message": "「ふんだ。もう決めた。\r\n絶対その気にさせてあげるもんっ」"
  },
  {
    "message": "………………"
  },
  {
    "message": "…………"
  },
  {
    "message": "……"
  },
  {
    "message": "そうして、お姉ちゃんの誘惑は\r\n日ごとに過激になっていって――"
  },
  {
    "name": "母",
    "message": "「優ーっ、お風呂空いたわよーっ！」"
  },
  {
    "name": "優",
    "message": "「あっ、はーいっ！」"
  },
  {
    "message": "階段の下から叫んでくるお母さんに応えながら、\r\n僕はお風呂場へと向かう。"
  },
  {
    "name": "美羽",
    "message": "「きゃっ。ゆうくんのエッチ♪」"
  },
  {
    "name": "優",
    "message": "「～～っっ！！？」"
  },
  {
    "name": "優",
    "message": "「ぼ、僕、もう少し後で入るっ！！」"
  },
  {
    "name": "美羽",
    "message": "「……むぅ。そこまで避けなくてもいいのに……」"
  },
  {
    "name": "優",
    "message": "「ふぁ……。おトイレ……」"
  },
  {
    "name": "美羽",
    "message": "「くすっ。またお姉ちゃんのコト、便女にする？」"
  },
  {
    "name": "優",
    "message": "「なっ――～～っっ！！？」"
  },
  {
    "name": "美羽",
    "message": "「あっ、コラっ！　ゆうくんっ！？」"
  },
  {
    "message": "う、うぅ……！　こんなの辛すぎる……！\r\nどこへ言ってもお姉ちゃんが誘惑してきて……！"
  },
  {
    "message": "まだ危険日まで三日もあるのに、\r\nちんちんパンパンだよぉ……！"
  },
  {
    "message": "学園でもずっと前屈みで過ごすハメになってるし……！\r\n体育の時間もお腹痛いって嘘ついて休んでるし……！"
  },
  {
    "message": "はぁはぁ、限界だ……！\r\nこれ以上、誘惑されたら僕はもう――"
  },
  {
    "message": "――そう思っていたのに、その翌日から\r\nお姉ちゃんの誘惑はぱたりとやんだ。"
  },
  {
    "name": "美羽",
    "message": "「ごちそうさま」"
  },
  {
    "message": "お姉ちゃんが箸を置いて、静かに立ち上がる。"
  },
  {
    "message": "そして、何も言わずに部屋へと戻っていった。"
  },
  {
    "message": "二日前からこの調子だ。誘惑してくるどころか、\r\n僕に喋りかけることさえほとんどなくなっちゃって……。"
  },
  {
    "message": "問題なくオナ禁を進めることはできるけれど……。\r\nでも、やっぱり寂しい……。"
  },
  {
    "name": "優",
    "message": "「でも、ついに明日なんだ……」"
  },
  {
    "message": "お姉ちゃんの危険日。待ちに待った日。"
  },
  {
    "message": "明日こそ僕はお姉ちゃんを孕ませる――！"
  },
  {
    "message": "この一週間で溜めに溜めた精子を、\r\nお姉ちゃんの子宮の中に注ぎ込むんだっ！！"
  },
  {
    "name": "優",
    "message": "「っっ！　は、はい？」"
  },
  {
    "name": "美羽",
    "message": "「お姉ちゃんだけど……ちょっといい？」"
  },
  {
    "name": "優",
    "message": "「えっ！？　あっ、その……！」"
  },
  {
    "message": "もしかして、お姉ちゃんが実力行使に……！？\r\nでもダメだ……！　明日じゃないと……！"
  },
  {
    "name": "美羽",
    "message": "「……やっぱり、入れてくれないんだ」"
  },
  {
    "name": "優",
    "message": "「お、お姉ちゃん……？」"
  },
  {
    "message": "お姉ちゃんの寂しげな声に、\r\n焦っていた頭が落ち着いていく。"
  },
  {
    "name": "美羽",
    "message": "「もしかしてゆうくん……お姉ちゃんのこと、\r\n嫌いになっちゃったのかな……？」"
  },
  {
    "name": "優",
    "message": "「えっ？　ど、どうして……！？」"
  },
  {
    "name": "美羽",
    "message": "「だって最近ずっとお姉ちゃんのこと避けてるし……。\r\n……あのエッチの後からだよね？　妊娠エッチの……」"
  },
  {
    "name": "美羽",
    "message": "「本当は……お姉ちゃんと子供作るの嫌だった？」"
  },
  {
    "name": "優",
    "message": "「そ、そんなこと――」"
  },
  {
    "name": "美羽",
    "message": "「う、ううん。いいの。うん、そうだよね。\r\nやっぱり、おかしいんだよね。お姉ちゃんがおかしいだけで」"
  },
  {
    "name": "美羽",
    "message": "「ご、ごめんねっ。もしものことがあっても気にしないで？\r\nゆうくんに迷惑はかけないから大丈夫……！」"
  },
  {
    "name": "優",
    "message": "「ち、ちがっ――お姉ちゃん、僕は……！」"
  },
  {
    "message": "慌てて部屋の外に出るけれど、お姉ちゃんは自分の部屋に\r\n戻っちゃったのか廊下にいなかった。"
  },
  {
    "message": "……そっか。お姉ちゃん、そんな風に思い詰めてて……。\r\nだから急に誘惑してくるのもやめて……。"
  },
  {
    "name": "優",
    "message": "「っっ……！」"
  },
  {
    "message": "――恥ずかしがらずにちゃんと言っておけば良かった。\r\nお姉ちゃんを孕ませるためにオナ禁してるってことを。"
  },
  {
    "message": "僕はいつもそうだ。恥ずかしがってばかりで、\r\nいつもそうやって失敗しちゃって……！"
  },
  {
    "name": "優",
    "message": "「…………」"
  },
  {
    "message": "今ここで理由を説明するのは簡単だ。"
  },
  {
    "message": "でも、それじゃきっとお姉ちゃんの心に伝わらない。\r\n上っ面だけの言葉だと勘違いされてしまうと思う。"
  },
  {
    "message": "だからこそ明日――明日、僕は態度で示そう。"
  },
  {
    "message": "お姉ちゃんに僕の子供を孕んで欲しいからこそ、\r\n僕はずっとオナ禁し続けていたんだって――"
  }
]